sqlalchemy_postgresql_relaxed/__init__.py
sqlalchemy_postgresql_relaxed/asyncpg.py
sqlalchemy_postgresql_relaxed/base.py
sqlalchemy_postgresql_relaxed/psycopg.py
sqlalchemy_postgresql_relaxed-0.1.2.dist-info/licenses/LICENSE
sqlalchemy_postgresql_relaxed-0.1.2.dist-info/METADATA
sqlalchemy_postgresql_relaxed-0.1.2.dist-info/WHEEL
sqlalchemy_postgresql_relaxed-0.1.2.dist-info/entry_points.txt
sqlalchemy_postgresql_relaxed-0.1.2.dist-info/top_level.txt
sqlalchemy_postgresql_relaxed-0.1.2.dist-info/RECORD
