Metadata-Version: 2.4
Name: sqlalchemy-postgresql-relaxed
Version: 0.1.2
Summary: Relaxed PostgreSQL dialects for SQLAlchemy
Author-email: Andreas Motl <andreas.motl@panodata.org>
License: MIT
Project-URL: changelog, https://github.com/pyveci/sqlalchemy-postgresql-relaxed/blob/main/CHANGES.rst
Project-URL: documentation, https://github.com/pyveci/sqlalchemy-postgresql-relaxed
Project-URL: homepage, https://github.com/pyveci/sqlalchemy-postgresql-relaxed
Project-URL: repository, https://github.com/pyveci/sqlalchemy-postgresql-relaxed
Keywords: dialect,postgresql,sqlalchemy
Classifier: Development Status :: 4 - Beta
Classifier: Environment :: Console
Classifier: Intended Audience :: Customer Service
Classifier: Intended Audience :: Developers
Classifier: Intended Audience :: Education
Classifier: Intended Audience :: Information Technology
Classifier: Intended Audience :: Manufacturing
Classifier: Intended Audience :: Science/Research
Classifier: Intended Audience :: System Administrators
Classifier: Intended Audience :: Telecommunications Industry
Classifier: License :: OSI Approved :: MIT License
Classifier: Operating System :: MacOS :: MacOS X
Classifier: Operating System :: Microsoft :: Windows
Classifier: Operating System :: POSIX :: Linux
Classifier: Operating System :: Unix
Classifier: Programming Language :: Python
Classifier: Programming Language :: Python :: 3 :: Only
Classifier: Programming Language :: Python :: 3.7
Classifier: Programming Language :: Python :: 3.8
Classifier: Programming Language :: Python :: 3.9
Classifier: Programming Language :: Python :: 3.10
Classifier: Programming Language :: Python :: 3.11
Classifier: Programming Language :: Python :: 3.12
Classifier: Programming Language :: Python :: 3.13
Classifier: Programming Language :: Python :: 3.14
Classifier: Topic :: Communications
Classifier: Topic :: Database
Classifier: Topic :: Documentation
Classifier: Topic :: Education
Classifier: Topic :: Office/Business
Classifier: Topic :: Scientific/Engineering
Classifier: Topic :: Software Development :: Code Generators
Classifier: Topic :: Software Development :: Libraries
Classifier: Topic :: Software Development :: Testing
Classifier: Topic :: System :: Archiving
Classifier: Topic :: System :: Systems Administration
Classifier: Topic :: Text Processing
Classifier: Topic :: Utilities
Requires-Python: >=3.7
License-File: LICENSE
Requires-Dist: asyncpg
Requires-Dist: psycopg[binary]
Requires-Dist: sqlalchemy<3,>=2
Provides-Extra: develop
Requires-Dist: poethepoet<1; extra == "develop"
Requires-Dist: proselint<1,>=0.16; python_version >= "3.10" and extra == "develop"
Requires-Dist: pyproject-fmt<3; extra == "develop"
Requires-Dist: ruff<0.15; extra == "develop"
Requires-Dist: validate-pyproject<1; extra == "develop"
Provides-Extra: release
Requires-Dist: build<2; extra == "release"
Requires-Dist: minibump<1; python_version >= "3.10" and extra == "release"
Requires-Dist: twine<7; extra == "release"
Provides-Extra: test
Requires-Dist: pandas<2.4; extra == "test"
Requires-Dist: polars[pyarrow]<1.37; extra == "test"
Requires-Dist: pytest<9; extra == "test"
Requires-Dist: pytest-asyncio<2; extra == "test"
Requires-Dist: pytest-cov<8; extra == "test"
Requires-Dist: sqlalchemy-cratedb; extra == "test"
Dynamic: license-file
